prediction_interval/__init__.py
prediction_interval/__main__.py
prediction_interval/_version.py
prediction_interval/cli.py
prediction_interval/models.py
prediction_interval-0.1.9.dist-info/METADATA
prediction_interval-0.1.9.dist-info/WHEEL
prediction_interval-0.1.9.dist-info/entry_points.txt
prediction_interval-0.1.9.dist-info/licenses/LICENSE
prediction_interval-0.1.9.dist-info/RECORD
