Metadata-Version: 2.4
Name: prediction_interval
Version: 0.1.9
Summary: Create Prediction Intervals such as Quantile Regression, Conformalized Quantile Regression, and bootstrapping using XGBoost
Project-URL: repository, https://github.com/dhisted/prediction_interval
Author: Dominic Histed
License: MIT
License-File: LICENSE
Classifier: Operating System :: OS Independent
Classifier: Programming Language :: Python
Classifier: Programming Language :: Python :: 3.9
Classifier: Programming Language :: Python :: 3.10
Classifier: Programming Language :: Python :: 3.11
Classifier: Programming Language :: Python :: 3.12
Classifier: Programming Language :: Python :: 3.13
Classifier: Programming Language :: Python :: Implementation :: CPython
Classifier: Topic :: Software Development :: Libraries :: Python Modules
Requires-Python: >=3.9
Requires-Dist: arrow>=1.3.0
Requires-Dist: asttokens>=3.0.0
Requires-Dist: binaryornot>=0.4.4
Requires-Dist: certifi>=2024.12.14
Requires-Dist: chardet>=5.2.0
Requires-Dist: charset-normalizer>=3.4.1
Requires-Dist: click>=8.1.8
Requires-Dist: colorama>=0.4.6
Requires-Dist: comm>=0.2.2
Requires-Dist: contourpy>=1.3.1
Requires-Dist: cookiecutter>=2.6.0
Requires-Dist: cycler>=0.12.1
Requires-Dist: debugpy>=1.8.11
Requires-Dist: decorator>=5.1.1
Requires-Dist: executing>=2.1.0
Requires-Dist: fonttools>=4.55.3
Requires-Dist: idna>=3.10
Requires-Dist: ipykernel>=6.29.5
Requires-Dist: ipython>=8.30.0
Requires-Dist: jedi>=0.19.2
Requires-Dist: jinja2>=3.1.5
Requires-Dist: joblib>=1.4.2
Requires-Dist: jupyter-client>=8.6.3
Requires-Dist: jupyter-core>=5.7.2
Requires-Dist: kiwisolver>=1.4.8
Requires-Dist: markdown-it-py>=3.0.0
Requires-Dist: markupsafe>=3.0.2
Requires-Dist: matplotlib-inline>=0.1.7
Requires-Dist: matplotlib>=3.10.0
Requires-Dist: mdurl>=0.1.2
Requires-Dist: nest-asyncio>=1.6.0
Requires-Dist: numpy>=2.0.0
Requires-Dist: packaging>=24.2
Requires-Dist: pandas>=2.2.3
Requires-Dist: parso>=0.8.4
Requires-Dist: pillow>=11.1.0
Requires-Dist: platformdirs>=4.3.6
Requires-Dist: prompt-toolkit>=3.0.48
Requires-Dist: psutil>=6.1.0
Requires-Dist: pure-eval>=0.2.3
Requires-Dist: pygments>=2.18.0
Requires-Dist: pyparsing>=3.2.1
Requires-Dist: python-dateutil>=2.9.0.post0
Requires-Dist: python-slugify>=8.0.4
Requires-Dist: pytz>=2024.2
Requires-Dist: pywin32>=308; sys_platform == 'win32'
Requires-Dist: pyyaml>=6.0.2
Requires-Dist: pyzmq>=26.2.0
Requires-Dist: requests>=2.32.3
Requires-Dist: rich>=13.9.4
Requires-Dist: scikit-learn>=1.6.1
Requires-Dist: scipy>=1.15.1
Requires-Dist: seaborn>=0.13.2
Requires-Dist: setuptools>=75.1.0
Requires-Dist: six>=1.17.0
Requires-Dist: stack-data>=0.6.3
Requires-Dist: text-unidecode>=1.3
Requires-Dist: threadpoolctl>=3.5.0
Requires-Dist: tornado>=6.4.2
Requires-Dist: traitlets>=5.14.3
Requires-Dist: types-python-dateutil>=2.9.0.20241206
Requires-Dist: tzdata>=2024.2
Requires-Dist: urllib3>=2.3.0
Requires-Dist: wcwidth>=0.2.13
Requires-Dist: wheel>=0.44.0
Requires-Dist: xgboost==3.0.0
Provides-Extra: test
Requires-Dist: mypy; extra == 'test'
Requires-Dist: pytest; extra == 'test'
Requires-Dist: pytest-cov; extra == 'test'
